dask_utils/__init__.py
dask_utils/client.py
dask_utils/config.py
dask_utils/decorators.py
dask_utils/packaging.py
dask_utils/queue.py
dask_utils-0.1.0.dist-info/METADATA
dask_utils-0.1.0.dist-info/WHEEL
dask_utils-0.1.0.dist-info/entry_points.txt
dask_utils-0.1.0.dist-info/RECORD
