Metadata-Version: 2.4
Name: dask-utils
Version: 0.1.0
Summary: daks lib utilities
Project-URL: Homepage, https://github.com/mhferjani/dask-utils
Project-URL: Repository, https://github.com/mhferjani/dask-utils
Author-email: Mohamed Hedi FERJANI <ferjani.mohamedhedi@gmail.com>
License: MIT
Keywords: dask,python
Classifier: License :: OSI Approved :: MIT License
Classifier: Programming Language :: Python :: 3
Requires-Python: >=3.10
Requires-Dist: dask[distributed]>=2025.12.0
Provides-Extra: dev
Requires-Dist: pytest-cov; extra == 'dev'
Requires-Dist: pytest-html; extra == 'dev'
Requires-Dist: pytest>=8.0.0; extra == 'dev'
Provides-Extra: doc
Requires-Dist: m2r2; extra == 'doc'
Requires-Dist: sphinx-rtd-theme; extra == 'doc'
Requires-Dist: sphinx>=7.2; extra == 'doc'
